haste/__init__.py
haste/_pipeline.py
haste/api.py
haste/cast_chunker.py
haste/cli.py
haste/cli_impl.py
haste/config.py
haste/core.py
haste/embeddings.py
haste/exporter.py
haste/identifiers.py
haste/index.py
haste/index_py.py
haste/judge.py
haste/metrics.py
haste/payload.py
haste/pipeline.py
haste/query_ingest.py
haste/query_utils.py
haste/retrieval.py
haste/retriever.py
haste/scanner.py
haste/selection.py
haste/ts_utils.py
haste/rankers/__init__.py
haste/rankers/hybrid.py
hastecontext-0.2.4.dist-info/licenses/LICENSE
hastecontext-0.2.4.dist-info/METADATA
hastecontext-0.2.4.dist-info/WHEEL
hastecontext-0.2.4.dist-info/entry_points.txt
hastecontext-0.2.4.dist-info/top_level.txt
hastecontext-0.2.4.dist-info/RECORD
