Metadata-Version: 2.4
Name: HasteContext
Version: 0.2.4
Summary: Parser-backed code-context compression using Tree-sitter
Home-page: https://github.com/Hacxmr/AST-Relevance-Compression
Author: Saish; Mitali Raj; Mushtaq
Author-email: 84446371+Bainshedone@users.noreply.github.com; 129144413+Hacxmr@users.noreply.github.com; Mushtaqsaeed577@gmail.com
Classifier: Development Status :: 4 - Beta
Classifier: Intended Audience :: Developers
Classifier: License :: OSI Approved :: MIT License
Classifier: Programming Language :: Python :: 3
Classifier: Programming Language :: Python :: 3.11
Classifier: Programming Language :: Python :: 3.12
Classifier: Programming Language :: Python :: 3.13
License-File: LICENSE
Requires-Dist: tree-sitter>=0.25.0
Requires-Dist: tree-sitter-language-pack<1.0.0,>=0.2.3
Requires-Dist: tiktoken<0.12.0,>=0.11.0
Requires-Dist: openai<2.0.0,>=1.99.9
Requires-Dist: numpy<3.0,>=1.26
Requires-Dist: rank-bm25<0.3.0,>=0.2.2
Requires-Dist: matplotlib<4.0.0,>=3.10.5
Requires-Dist: setuptools
Requires-Dist: wheel
Requires-Dist: twine
Requires-Dist: sentence-transformers
Dynamic: author
Dynamic: author-email
Dynamic: classifier
Dynamic: description
Dynamic: description-content-type
Dynamic: home-page
Dynamic: license-file
Dynamic: requires-dist
Dynamic: summary
